DatawhaleQianghuaXuexiZhongwenJiaochengFix1/README.md
DatawhaleQianghuaXuexiZhongwenJiaochengFix1/__init__.py
DatawhaleQianghuaXuexiZhongwenJiaochengFix1/__main__.py
DatawhaleQianghuaXuexiZhongwenJiaochengFix1/file.epub
DatawhaleQianghuaXuexiZhongwenJiaochengFix1/index.html
DatawhaleQianghuaXuexiZhongwenJiaochengFix1/css/__init__.py
DatawhaleQianghuaXuexiZhongwenJiaochengFix1/css/annotations.css
DatawhaleQianghuaXuexiZhongwenJiaochengFix1/css/main.css
DatawhaleQianghuaXuexiZhongwenJiaochengFix1/css/normalize.css
DatawhaleQianghuaXuexiZhongwenJiaochengFix1/css/popup.css
DatawhaleQianghuaXuexiZhongwenJiaochengFix1/font/__init__.py
DatawhaleQianghuaXuexiZhongwenJiaochengFix1/font/fontello.eot
DatawhaleQianghuaXuexiZhongwenJiaochengFix1/font/fontello.svg
DatawhaleQianghuaXuexiZhongwenJiaochengFix1/font/fontello.ttf
DatawhaleQianghuaXuexiZhongwenJiaochengFix1/font/fontello.woff
DatawhaleQianghuaXuexiZhongwenJiaochengFix1/img/__init__.py
DatawhaleQianghuaXuexiZhongwenJiaochengFix1/img/annotator-glyph-sprite.png
DatawhaleQianghuaXuexiZhongwenJiaochengFix1/img/annotator-icon-sprite.png
DatawhaleQianghuaXuexiZhongwenJiaochengFix1/img/apple-touch-icon.png
DatawhaleQianghuaXuexiZhongwenJiaochengFix1/img/cancelfullscreen.png
DatawhaleQianghuaXuexiZhongwenJiaochengFix1/img/close.png
DatawhaleQianghuaXuexiZhongwenJiaochengFix1/img/fullscreen.png
DatawhaleQianghuaXuexiZhongwenJiaochengFix1/img/loader.gif
DatawhaleQianghuaXuexiZhongwenJiaochengFix1/img/menu-icon.png
DatawhaleQianghuaXuexiZhongwenJiaochengFix1/img/save.png
DatawhaleQianghuaXuexiZhongwenJiaochengFix1/img/saved.png
DatawhaleQianghuaXuexiZhongwenJiaochengFix1/img/settings-s.png
DatawhaleQianghuaXuexiZhongwenJiaochengFix1/img/settings.png
DatawhaleQianghuaXuexiZhongwenJiaochengFix1/img/star.png
DatawhaleQianghuaXuexiZhongwenJiaochengFix1/js/__init__.py
DatawhaleQianghuaXuexiZhongwenJiaochengFix1/js/epub.js
DatawhaleQianghuaXuexiZhongwenJiaochengFix1/js/epub.min.js
datawhale_qianghua_xuexi_zhongwen_jiaocheng_fix1-2025.3.25.0.dist-info/METADATA
datawhale_qianghua_xuexi_zhongwen_jiaocheng_fix1-2025.3.25.0.dist-info/WHEEL
datawhale_qianghua_xuexi_zhongwen_jiaocheng_fix1-2025.3.25.0.dist-info/entry_points.txt
datawhale_qianghua_xuexi_zhongwen_jiaocheng_fix1-2025.3.25.0.dist-info/top_level.txt
datawhale_qianghua_xuexi_zhongwen_jiaocheng_fix1-2025.3.25.0.dist-info/RECORD
